{
	"mode": "device2",
	"lang": "ko",
	"General": {
		"useFuction": {
			"ftp": false,
			"sntp": false,
			"diagnosis_main": false,
			"diagnosis_sub": false
		},
		"deviceInfo": {
			"mac_address": "08bfb86e4d5f",
			"serial_number": "08bfb86e4d5f",
			"name": "",
			"location": ""
		},
		"tcpip": {
			"ip_address": "192.168.2.10",
			"subnet_mask": "255.255.255.0",
			"gateway": "192.168.2.1",
			"dnsserver": "8.8.8.8"
		},
		"modbus": {
			"isserial": false,
			"tcp_port": "502",
			"modbus_id": "1",
			"baud_rate": "4",
			"parity": "0"
		},
		"demand_interval": "2",
		"pf_sign":0,
		"va_type":0,
		"ftpInfo": {
			"isManual": false,
			"host": "192.168.100.100",
			"port": "21",
			"id": "sig",
			"pass": "signal",
			"upload_main": "",
			"upload_sub": ""
		},
		"sntpInfo": {
			"host": "",
			"timezone": "Asia/Seoul"
		}
	},
	"channel": [
		{
			"channel": "Main",
			"Enable": 1,
			"PowerQuality": 1,
			"ctInfo": {
				"direction": [
					0,
					0,
					0
				],
				"startingcurrent": 100,
				"inorminal": 100,
				"ct1": 100,
				"ct2": 1,
				"zctscale": 1000,
				"zcttpye": 1
			},
			"demand": {
				"target": ""
			},
			"ptInfo": {
				"wiringmode": 1,
				"linefrequency": 60,
				"vnorminal": 220,
				"pt1": 220,
				"pt2": 220
			},
			"assetInfo": {
				"name": "PowerSupply",
				"type": "PowerSupply",
				"nickname": "1차측"
			},
			"eventInfo": {
				"oc_action": 0,
				"oc_level": 120,
				"oc_holdofftime": 500,
				"tv_action": 0,
				"tv_level": 4,
				"tv_holdofftime": 200,
				"tv_fastchange": 0,
				"tc_action": 0,
				"tc_level": 4,
				"tc_holdofftime": 200,
				"inter_action": 0,
				"inter_level": 5,
				"inter_holdofftime": 500,
				"sag_action": 0,
				"sag_level": 80,
				"sag_holdofftime": 500,
				"swell_action": 0,
				"swell_level": 120,
				"swell_holdofftime": 500,
				"tc_fastchange": 0
			},
			"sampling": {
				"rate": 8000,
				"duration": 5,
				"period": 5
			},
			"n_kva": 0,
			"trendInfo": {
				"period": 5,
				"params": [
					"None",
					"None",
					"None",
					"None",
					"None",
					"None",
					"None",
					"None"
				]
			},
			"alarm": {
				"1": [
					0,
					0,
					1,
					0
				],
				"2": [
					0,
					0,
					1,
					0
				],
				"3": [
					0,
					0,
					1,
					0
				],
				"4": [
					0,
					0,
					1,
					0
				],
				"5": [
					0,
					0,
					1,
					0
				],
				"6": [
					0,
					0,
					1,
					0
				],
				"7": [
					0,
					0,
					1,
					0
				],
				"8": [
					0,
					0,
					1,
					0
				],
				"9": [
					0,
					0,
					1,
					0
				],
				"10": [
					0,
					0,
					1,
					0
				],
				"11": [
					0,
					0,
					1,
					0
				],
				"12": [
					0,
					0,
					1,
					0
				],
				"13": [
					0,
					0,
					1,
					0
				],
				"14": [
					0,
					0,
					1,
					0
				],
				"15": [
					0,
					0,
					1,
					0
				],
				"16": [
					0,
					0,
					1,
					0
				],
				"17": [
					0,
					0,
					1,
					0
				],
				"18": [
					0,
					0,
					1,
					0
				],
				"19": [
					0,
					0,
					1,
					0
				],
				"20": [
					0,
					0,
					1,
					0
				],
				"21": [
					0,
					0,
					1,
					0
				],
				"22": [
					0,
					0,
					1,
					0
				],
				"23": [
					0,
					0,
					1,
					0
				],
				"24": [
					0,
					0,
					1,
					0
				],
				"25": [
					0,
					0,
					1,
					0
				],
				"26": [
					0,
					0,
					1,
					0
				],
				"27": [
					0,
					0,
					1,
					0
				],
				"28": [
					0,
					0,
					1,
					0
				],
				"29": [
					0,
					0,
					1,
					0
				],
				"30": [
					0,
					0,
					1,
					0
				],
				"31": [
					0,
					0,
					1,
					0
				],
				"32": [
					0,
					0,
					1,
					0
				],
				"CompareTimeDelay": 1
			}
		},
		{
			"channel": "Sub",
			"Enable": 1,
			"PowerQuality": 1,
			"ctInfo": {
				"direction": [
					0,
					0,
					0
				],
				"startingcurrent": 100,
				"inorminal": 100,
				"ct1": 100,
				"ct2": 1,
				"zctscale": 1000,
				"zcttpye": 1
			},
			"demand": {
				"target": ""
			},
			"ptInfo": {
				"wiringmode": 1,
				"linefrequency": 60,
				"vnorminal": 220,
				"pt1": 220,
				"pt2": 220
			},
			"assetInfo": {
				"name": "Transformer",
				"type": "Transformer",
				"nickname": "소내변압기"
			},
			"eventInfo": {
				"oc_action": 0,
				"oc_level": 120,
				"oc_holdofftime": 500,
				"tv_action": 0,
				"tv_level": 4,
				"tv_holdofftime": 200,
				"tv_fastchange": 0,
				"tc_action": 0,
				"tc_level": 4,
				"tc_holdofftime": 200,
				"inter_action": 0,
				"inter_level": 5,
				"inter_holdofftime": 500,
				"sag_action": 0,
				"sag_level": 80,
				"sag_holdofftime": 500,
				"swell_action": 0,
				"swell_level": 120,
				"swell_holdofftime": 500,
				"tc_fastchange": 0
			},
			"sampling": {
				"rate": 8000,
				"duration": 5,
				"period": 5
			},
			"n_kva": "3000",
			"trendInfo": {
				"period": 5,
				"params": [
					"None",
					"None",
					"None",
					"None",
					"None",
					"None",
					"None",
					"None"
				]
			},
			"alarm": {
				"1": [
					0,
					0,
					1,
					0
				],
				"2": [
					0,
					0,
					1,
					0
				],
				"3": [
					0,
					0,
					1,
					0
				],
				"4": [
					0,
					0,
					1,
					0
				],
				"5": [
					0,
					0,
					1,
					0
				],
				"6": [
					0,
					0,
					1,
					0
				],
				"7": [
					0,
					0,
					1,
					0
				],
				"8": [
					0,
					0,
					1,
					0
				],
				"9": [
					0,
					0,
					1,
					0
				],
				"10": [
					0,
					0,
					1,
					0
				],
				"11": [
					0,
					0,
					1,
					0
				],
				"12": [
					0,
					0,
					1,
					0
				],
				"13": [
					0,
					0,
					1,
					0
				],
				"14": [
					0,
					0,
					1,
					0
				],
				"15": [
					0,
					0,
					1,
					0
				],
				"16": [
					0,
					0,
					1,
					0
				],
				"17": [
					0,
					0,
					1,
					0
				],
				"18": [
					0,
					0,
					1,
					0
				],
				"19": [
					0,
					0,
					1,
					0
				],
				"20": [
					0,
					0,
					1,
					0
				],
				"21": [
					0,
					0,
					1,
					0
				],
				"22": [
					0,
					0,
					1,
					0
				],
				"23": [
					0,
					0,
					1,
					0
				],
				"24": [
					0,
					0,
					1,
					0
				],
				"25": [
					0,
					0,
					1,
					0
				],
				"26": [
					0,
					0,
					1,
					0
				],
				"27": [
					0,
					0,
					1,
					0
				],
				"28": [
					0,
					0,
					1,
					0
				],
				"29": [
					0,
					0,
					1,
					0
				],
				"30": [
					0,
					0,
					1,
					0
				],
				"31": [
					0,
					0,
					1,
					0
				],
				"32": [
					0,
					0,
					1,
					0
				],
				"CompareTimeDelay": 1
			}
		}
	]
}